FileManagerPro/FileManagerPro.py
FileManagerPro/__init__.py
FileManagerPro-1.0.1.dist-info/LICENSE
FileManagerPro-1.0.1.dist-info/METADATA
FileManagerPro-1.0.1.dist-info/WHEEL
FileManagerPro-1.0.1.dist-info/top_level.txt
FileManagerPro-1.0.1.dist-info/RECORD
